hammy/__init__.py
hammy/hammy_main.py
hammy/load.py
hammy/Hammy_Detector/__init__.py
hammy/Hammy_Detector/detector.py
hammy/Hammy_Filter/__init__.py
hammy/Hammy_Filter/filter.py
hammy/Hammy_Generator/__init__.py
hammy/Hammy_Generator/generator.py
hammy/Hammy_Generator/planner.py
hammy/Hammy_LCA/__init__.py
hammy/Hammy_LCA/construction.py
hammy/Hammy_LCA/lca.py
hammy/Hammy_LCA/material.py
hammy/Hammy_Optimizer/__init__.py
hammy/Hammy_Optimizer/cluster.py
hammy/Hammy_Optimizer/correlation.py
hammy/Hammy_Optimizer/objective.py
hammy/Hammy_Optimizer/sampler.py
hammy/Hammy_Parametrizer/__init__.py
hammy/Hammy_Parametrizer/block.py
hammy/Hammy_Parametrizer/face.py
hammy/Hammy_Parametrizer/mass_data.py
hammy/Hammy_Parametrizer/massing.py
hammy/Hammy_Penalty/__init__.py
hammy/Hammy_Penalty/penalty.py
hammy/Hammy_Utils/__init__.py
hammy/Hammy_Utils/util.py
hammy/Hammy_Utils/util2.py
hammy/Hammy_Utils/util3.py
hammy/datas/lib/lca_lib/constr_info_ee.json
hammy/datas/lib/lca_lib/mat_lib_v21.json
hammy/datas/lib/lca_lib/mat_lib_v23.json
hammy/datas/lib/mass_lib/bldg_form.json
hammy/datas/lib/mass_lib/con_lib.json
hammy/datas/lib/mass_lib/ref_lib.json
hammy/datas/lib/mass_lib/test.json
hammy/datas/surrogate_models/ASE_rf_reg_pred_mod.pkl
hammy/datas/surrogate_models/sDA_rf_reg_pred_mod.pkl
hammy/datas/surrogate_models/total_energy_demand_mlp_reg_pred_mod.pkl
hammy/datas/surrogate_models/total_energy_demand_rf_reg_2050_pred_mod.pkl
hammy/datas/surrogate_models/total_energy_demand_rf_reg_2070_pred_mod.pkl
hammy/datas/surrogate_models/total_energy_demand_rf_reg_pred_mod.pkl
hammy/datas/temp/00_initial_data.json
hammy/datas/temp/building_data.json
hammy/datas/temp/plan_data.json
hammy/datas/temp/outputs/00_sample.json
hammy/datas/temp/outputs/01_geo_data.json
hammy/datas/temp/outputs/02_res_repo.json
hammy/datas/temp/outputs/03_objs.json
hammy/datas/temp/outputs/error_repo/err_samples.json
hammy/pyarmor_runtime_000000/__init__.py
hammy/pyarmor_runtime_000000/pyarmor_runtime.pyd
hammy-0.1.0.dist-info/LICENSE
hammy-0.1.0.dist-info/METADATA
hammy-0.1.0.dist-info/WHEEL
hammy-0.1.0.dist-info/top_level.txt
hammy-0.1.0.dist-info/RECORD
