Metadata-Version: 2.1
Name: hammy
Version: 0.1.0
Summary: optimization tool for building performance
Home-page: https://github.com/HammyTwoOfficial/hammy
Author: YuxinQiuShuangyingXu
Author-email: hammytwo.official@gmail.com
License: MIT
Classifier: License :: OSI Approved :: MIT License
Classifier: Programming Language :: Python :: 3.10
Classifier: Operating System :: OS Independent
Requires-Python: >=3.7
License-File: LICENSE
Requires-Dist: bson >=0.5.10
Provides-Extra: dev
Requires-Dist: pytest >=7.0 ; extra == 'dev'
Requires-Dist: twine >=4.0.2 ; extra == 'dev'
